compass_labyrinth/__init__.py
compass_labyrinth/constants.py
compass_labyrinth/utils.py
compass_labyrinth/behavior/__init__.py
compass_labyrinth/behavior/behavior_metrics/__init__.py
compass_labyrinth/behavior/behavior_metrics/simulation_modeling/__init__.py
compass_labyrinth/behavior/behavior_metrics/simulation_modeling/explore_exploit_agent.py
compass_labyrinth/behavior/behavior_metrics/simulation_modeling/multi_agent.py
compass_labyrinth/behavior/behavior_metrics/simulation_modeling/simulated_agent.py
compass_labyrinth/behavior/behavior_metrics/task_performance_analysis/__init__.py
compass_labyrinth/behavior/behavior_metrics/task_performance_analysis/performance_metrics.py
compass_labyrinth/behavior/behavior_metrics/task_performance_analysis/success_metrics.py
compass_labyrinth/behavior/behavior_metrics/task_performance_analysis/trajectory_analysis.py
compass_labyrinth/behavior/pose_estimation/__init__.py
compass_labyrinth/behavior/pose_estimation/dlc_utils.py
compass_labyrinth/behavior/preprocessing/__init__.py
compass_labyrinth/behavior/preprocessing/preprocessing_utils.py
compass_labyrinth/compass/__init__.py
compass_labyrinth/compass/level_1/__init__.py
compass_labyrinth/compass/level_1/momentu.py
compass_labyrinth/compass/level_1/prep_data.py
compass_labyrinth/compass/level_1/visualization.py
compass_labyrinth/compass/level_2/__init__.py
compass_labyrinth/compass/level_2/datastreams.py
compass_labyrinth/compass/level_2/model.py
compass_labyrinth/compass/level_2/plots.py
compass_labyrinth/compass/level_2/utils.py
compass_labyrinth/data/4step_adjacency_matrix.csv
compass_labyrinth/data/value_function_per_grid_cell.csv
compass_labyrinth/post_hoc_analysis/__init__.py
compass_labyrinth/post_hoc_analysis/level_1/__init__.py
compass_labyrinth/post_hoc_analysis/level_1/bout_analysis.py
compass_labyrinth/post_hoc_analysis/level_1/grid_heatmap.py
compass_labyrinth/post_hoc_analysis/level_1/spatial_analysis.py
compass_labyrinth-0.1.1.dist-info/licenses/LICENSE.md
compass_labyrinth-0.1.1.dist-info/METADATA
compass_labyrinth-0.1.1.dist-info/WHEEL
compass_labyrinth-0.1.1.dist-info/top_level.txt
compass_labyrinth-0.1.1.dist-info/RECORD
