Metadata-Version: 2.4
Name: compass_labyrinth
Version: 0.1.1
Summary: A unified computational and behavioral framework for analyzing goal-directed navigation in complex maze environments using hierarchical probabilistic models.
Author: Shreya Bangera, Patrick Honma, Luiz Tauffer
License: MIT
Project-URL: homepage, https://github.com/CoMPASS-Framework/CoMPASS-Labyrinth
Project-URL: repository, https://github.com/CoMPASS-Framework/CoMPASS-Labyrinth
Project-URL: documentation, https://github.com/CoMPASS-Framework/CoMPASS-Labyrinth/blob/main/README.md
Keywords: compass,navigation,behavioral-modeling,hmm,neural-analysis,eeg,decision-making
Requires-Python: >=3.11
License-File: LICENSE.md
Requires-Dist: numpy
Requires-Dist: pandas
Requires-Dist: scipy
Requires-Dist: scikit-learn
Requires-Dist: joblib
Requires-Dist: matplotlib
Requires-Dist: seaborn
Requires-Dist: plotly
Requires-Dist: geopandas
Requires-Dist: shapely
Requires-Dist: statsmodels
Requires-Dist: xgboost
Requires-Dist: shap
Requires-Dist: hmmlearn
Requires-Dist: umap-learn
Requires-Dist: mne
Requires-Dist: pyedflib
Requires-Dist: opencv-python
Requires-Dist: openpyxl
Requires-Dist: PyYAML
Provides-Extra: dev
Requires-Dist: jupyterlab>=4.3.5; extra == "dev"
Requires-Dist: ipykernel; extra == "dev"
Requires-Dist: black>=23.0.0; extra == "dev"
Provides-Extra: tests
Requires-Dist: pytest>=7.0.0; extra == "tests"
Requires-Dist: pytest-cov; extra == "tests"
Dynamic: license-file
